open_fdd/__init__.py
open_fdd/air_handling_unit/__init__.py
open_fdd/air_handling_unit/faults/__init__.py
open_fdd/air_handling_unit/faults/fault_condition_eight.py
open_fdd/air_handling_unit/faults/fault_condition_eleven.py
open_fdd/air_handling_unit/faults/fault_condition_fifteen.py
open_fdd/air_handling_unit/faults/fault_condition_five.py
open_fdd/air_handling_unit/faults/fault_condition_four.py
open_fdd/air_handling_unit/faults/fault_condition_fourteen.py
open_fdd/air_handling_unit/faults/fault_condition_nine.py
open_fdd/air_handling_unit/faults/fault_condition_one.py
open_fdd/air_handling_unit/faults/fault_condition_seven.py
open_fdd/air_handling_unit/faults/fault_condition_six.py
open_fdd/air_handling_unit/faults/fault_condition_sixteen.py
open_fdd/air_handling_unit/faults/fault_condition_ten.py
open_fdd/air_handling_unit/faults/fault_condition_thirteen.py
open_fdd/air_handling_unit/faults/fault_condition_three.py
open_fdd/air_handling_unit/faults/fault_condition_twelve.py
open_fdd/air_handling_unit/faults/fault_condition_two.py
open_fdd/air_handling_unit/faults/helper_utils.py
open_fdd/air_handling_unit/reports/__init__.py
open_fdd/air_handling_unit/reports/fault_report.py
open_fdd/chiller_plant/__init__.py
open_fdd/chiller_plant/faults/__init__.py
open_fdd/chiller_plant/faults/fault_condition_one.py
open_fdd/chiller_plant/faults/fault_condition_two.py
open_fdd/tests/__init__.py
open_fdd/tests/ahu/__init__.py
open_fdd/tests/ahu/test_ahu_fc1.py
open_fdd/tests/ahu/test_ahu_fc10.py
open_fdd/tests/ahu/test_ahu_fc11.py
open_fdd/tests/ahu/test_ahu_fc12.py
open_fdd/tests/ahu/test_ahu_fc13.py
open_fdd/tests/ahu/test_ahu_fc14.py
open_fdd/tests/ahu/test_ahu_fc15.py
open_fdd/tests/ahu/test_ahu_fc16.py
open_fdd/tests/ahu/test_ahu_fc2.py
open_fdd/tests/ahu/test_ahu_fc3.py
open_fdd/tests/ahu/test_ahu_fc4.py
open_fdd/tests/ahu/test_ahu_fc5.py
open_fdd/tests/ahu/test_ahu_fc6.py
open_fdd/tests/ahu/test_ahu_fc7.py
open_fdd/tests/ahu/test_ahu_fc8.py
open_fdd-0.1.9.dist-info/licenses/LICENSE
open_fdd-0.1.9.dist-info/METADATA
open_fdd-0.1.9.dist-info/WHEEL
open_fdd-0.1.9.dist-info/top_level.txt
open_fdd-0.1.9.dist-info/RECORD
