Metadata-Version: 2.4
Name: open_fdd
Version: 0.1.9
Summary: A package for fault detection and diagnosis in HVAC systems
Home-page: https://bbartling.github.io/open-fdd/
Author: Ben Bartling
Author-email: ben.bartling@gmail.com
Classifier: Programming Language :: Python :: 3
Classifier: License :: OSI Approved :: MIT License
Classifier: Operating System :: OS Independent
Requires-Python: >=3.6
License-File: LICENSE
Requires-Dist: pandas
Requires-Dist: matplotlib
Requires-Dist: pytest
Dynamic: author
Dynamic: author-email
Dynamic: classifier
Dynamic: description
Dynamic: description-content-type
Dynamic: home-page
Dynamic: license-file
Dynamic: requires-dist
Dynamic: requires-python
Dynamic: summary
